slid/__init__.py
slid-0.2.1.dist-info/LICENSE
slid-0.2.1.dist-info/METADATA
slid-0.2.1.dist-info/WHEEL
slid-0.2.1.dist-info/top_level.txt
slid-0.2.1.dist-info/RECORD
