Metadata-Version: 2.1
Name: slid
Version: 0.2.1
Summary: A package for making alert windows that slide close.
Home-page: https://pypi.com/project/slid
Author: Ram Taralekar
Author-email: ramtaralekar@outlook.com
License: UNKNOWN
Platform: UNKNOWN
Classifier: Programming Language :: Python :: 3
Classifier: License :: OSI Approved :: MIT License
Classifier: Operating System :: OS Independent
Requires-Python: >=3.6
